broadlinkhacktools/__init__.py
broadlinkhacktools/decryptor.py
broadlinkhacktools/filter.py
broadlinkhacktools/printer.py
broadlinkhacktools/storage.py
broadlinkhacktools/protocol/__init__.py
broadlinkhacktools/protocol/const.py
broadlinkhacktools/protocol/helpers.py
broadlinkhacktools/protocol/packets.py
broadlinkhacktools-0.0.1.dist-info/LICENSE
broadlinkhacktools-0.0.1.dist-info/METADATA
broadlinkhacktools-0.0.1.dist-info/WHEEL
broadlinkhacktools-0.0.1.dist-info/top_level.txt
broadlinkhacktools-0.0.1.dist-info/RECORD
