Metadata-Version: 2.1
Name: broadlinkhacktools
Version: 0.0.1
Summary: Tools for hacking the Broadlink protocol.
Home-page: UNKNOWN
Author: Felipe Martins Diel
Author-email: felipemartinsdiel@gmail.com
License: MIT
Platform: UNKNOWN
Classifier: Programming Language :: Python :: 3
Classifier: License :: OSI Approved :: MIT License
Classifier: Operating System :: OS Independent
Requires-Dist: beautifultable (>=0.8)
Requires-Dist: cryptography (>=2.8)
